requesto/Exceptions.py
requesto/PostgresDb.py
requesto/SqliteDb.py
requesto/User.py
requesto/__init__.py
requesto/requesto.py
requesto_py-1.2.0.1.dist-info/LICENSE
requesto_py-1.2.0.1.dist-info/METADATA
requesto_py-1.2.0.1.dist-info/WHEEL
requesto_py-1.2.0.1.dist-info/top_level.txt
requesto_py-1.2.0.1.dist-info/RECORD
