Metadata-Version: 2.1
Name: requesto-py
Version: 1.2.0.1
Summary: Lightweight python wrapper library for psycopg2 and sqlite3 databases without tons of useless code.
Author-email: NaroMori <reply.naromori@google.com>
Project-URL: Homepage, https://github.com/SOLIDusr/requesto-py
Project-URL: Issues, https://github.com/SOLIDusr/requesto-py/issues
Classifier: Programming Language :: Python :: 3
Classifier: License :: OSI Approved :: GNU General Public License v3 (GPLv3)
Classifier: Operating System :: OS Independent
Requires-Python: >=3.10
License-File: LICENSE
